test/__init__.py
test/bigquery_client_integration_test.py
test/bigquery_client_test.py
test/bigquery_streaming_insertion_uploader_test.py
test/frame_metrics_reader_test.py
test/frame_size_reader_test.py
test/metric_data_upload_client_test.py
test/metric_data_upload_main_test.py
test/psnr_reader_test.py
test/schema_builder_test.py
test/ssim_reader_test.py
test/video_quality_data_handler_test.py
vpxhw_db_data_uploader-0.9.dist-info/DESCRIPTION.rst
vpxhw_db_data_uploader-0.9.dist-info/METADATA
vpxhw_db_data_uploader-0.9.dist-info/RECORD
vpxhw_db_data_uploader-0.9.dist-info/WHEEL
vpxhw_db_data_uploader-0.9.dist-info/metadata.json
vpxhw_db_data_uploader-0.9.dist-info/top_level.txt
