Metadata-Version: 2.0
Name: vpxhw-db-data-uploader
Version: 0.9
Summary: package for uploading data to vpxhw database
Home-page: UNKNOWN
Author: Ray Xu
Author-email: rxuniverse@google.com
License: UNKNOWN
Platform: UNKNOWN
Classifier: Programming Language :: Python :: 2
Classifier: License :: OSI Approved :: MIT License
Classifier: Operating System :: OS Independent
Requires-Dist: google-cloud-bigquery (==0.24.0)
Requires-Dist: google-cloud-storage (==1.1.1)
Requires-Dist: httplib2 (==0.10.3)
Requires-Dist: matplotlib
Requires-Dist: mock
Requires-Dist: mysqlclient
Requires-Dist: pandas (>=0.20.1)
Requires-Dist: pytest
